README.rst
setup.py
districtsTk/__init__.py
districtsTk/districtsTk.py
districtsTk.egg-info/PKG-INFO
districtsTk.egg-info/SOURCES.txt
districtsTk.egg-info/dependency_links.txt
districtsTk.egg-info/top_level.txt