Metadata-Version: 1.1
Name: districtsTk
Version: 0.5
Summary: A script to check whether or not a point on earth is within a given district.
Home-page: https://hannover.freifunk.net
Author: Aiyion and Raute from Freifunk Hannover
Author-email: dev@hannover.freifunk.net
License: MIT
Keywords: district localisation geocoordinates
Platform: UNKNOWN
Classifier: Development Status :: 4 - Beta
Classifier: Intended Audience :: Developers
Classifier: Topic :: Software Development :: Libraries :: Python Modules
Classifier: License :: OSI Approved :: MIT License
Classifier: Programming Language :: Python :: 3.6
